aa_ui/__init__.py
aa_ui/__main__.py
aa_ui/action.py
aa_ui/agenta_cli/README.md
aa_ui/agenta_cli/agenta/__init__.py
aa_ui/agenta_cli/agenta/cli/evaluation_commands.py
aa_ui/agenta_cli/agenta/cli/helper.py
aa_ui/agenta_cli/agenta/cli/main.py
aa_ui/agenta_cli/agenta/cli/telemetry.py
aa_ui/agenta_cli/agenta/cli/variant_commands.py
aa_ui/agenta_cli/agenta/cli/variant_configs.py
aa_ui/agenta_cli/agenta/client/Readme.md
aa_ui/agenta_cli/agenta/client/__init__.py
aa_ui/agenta_cli/agenta/client/api.py
aa_ui/agenta_cli/agenta/client/api_models.py
aa_ui/agenta_cli/agenta/client/backend/__init__.py
aa_ui/agenta_cli/agenta/client/backend/client.py
aa_ui/agenta_cli/agenta/client/backend/core/__init__.py
aa_ui/agenta_cli/agenta/client/backend/core/api_error.py
aa_ui/agenta_cli/agenta/client/backend/core/client_wrapper.py
aa_ui/agenta_cli/agenta/client/backend/core/datetime_utils.py
aa_ui/agenta_cli/agenta/client/backend/core/jsonable_encoder.py
aa_ui/agenta_cli/agenta/client/backend/core/remove_none_from_dict.py
aa_ui/agenta_cli/agenta/client/backend/errors/__init__.py
aa_ui/agenta_cli/agenta/client/backend/errors/unprocessable_entity_error.py
aa_ui/agenta_cli/agenta/client/backend/types/__init__.py
aa_ui/agenta_cli/agenta/client/backend/types/add_variant_from_base_and_config_response.py
aa_ui/agenta_cli/agenta/client/backend/types/aggregated_result.py
aa_ui/agenta_cli/agenta/client/backend/types/app.py
aa_ui/agenta_cli/agenta/client/backend/types/app_variant_output.py
aa_ui/agenta_cli/agenta/client/backend/types/app_variant_output_extended.py
aa_ui/agenta_cli/agenta/client/backend/types/app_variant_revision.py
aa_ui/agenta_cli/agenta/client/backend/types/base_output.py
aa_ui/agenta_cli/agenta/client/backend/types/body_import_testset.py
aa_ui/agenta_cli/agenta/client/backend/types/config_db.py
aa_ui/agenta_cli/agenta/client/backend/types/container_templates_response.py
aa_ui/agenta_cli/agenta/client/backend/types/create_app_output.py
aa_ui-1.0.505.dist-info/METADATA
aa_ui-1.0.505.dist-info/WHEEL
aa_ui-1.0.505.dist-info/entry_points.txt
aa_ui-1.0.505.dist-info/RECORD
